{"ymList":["202301","202302","202303","202304","202305","202306","202307","202308","202309","202310","202311","202312","202401","202402","202403","202404","202405","202406","202407","202408","202409","202410","202411","202412","202501","202502","202503","202504","202505","202506","202507","202508","202509","202510","202511","202512","202601","202602","202603","202604","202605"],"ymMin":"202301","ymMax":"202605","nMonths":41,"updatedAt":"2026-06-06","filters":{"sido":["강원특별자치도","경기도","경상남도","경상북도","광주광역시","대구광역시","대전광역시","부산광역시","서울특별시","세종특별자치시","울산광역시","인천광역시","전라남도","전북특별자치도","제주특별자치도","충청남도","충청북도"],"sggBySido":{"경상남도":["거제시","거창군","고성군","김해시","남해군","밀양시","사천시","산청군","양산시","의령군","진주시","창녕군","창원시 마산합포구","창원시 마산회원구","창원시 성산구","창원시 의창구","창원시 진해구","통영시","하동군","함안군","함양군","합천군"],"경기도":["가평군","고양시 덕양구","고양시 일산동구","고양시 일산서구","과천시","광명시","광주시","구리시","군포시","김포시","남양주시","동두천시","부천시 소사구","부천시 오정구","부천시 원미구","성남시 분당구","성남시 수정구","성남시 중원구","수원시 권선구","수원시 영통구","수원시 장안구","수원시 팔달구","시흥시","안산시 단원구","안산시 상록구","안성시","안양시 동안구","안양시 만안구","양주시","양평군","여주시","연천군","오산시","용인시 기흥구","용인시 수지구","용인시 처인구","의왕시","의정부시","이천시","파주시","평택시","포천시","하남시","화성시"],"제주특별자치도":["서귀포시","제주시"],"부산광역시":["강서구","금정구","기장군","남구","동구","동래구","부산진구","북구","사상구","사하구","서구","수영구","연제구","영도구","중구","해운대구"],"서울특별시":["강남구","강동구","강북구","강서구","관악구","광진구","구로구","금천구","노원구","도봉구","동대문구","동작구","마포구","서대문구","서초구","성동구","성북구","송파구","양천구","영등포구","용산구","은평구","종로구","중구","중랑구"],"인천광역시":["강화군","계양구","남동구","동구","미추홀구","부평구","서구","연수구","옹진군","중구"],"충청남도":["계룡시","공주시","금산군","논산시","당진시","보령시","부여군","서산시","서천군","아산시","예산군","천안시 동남구","천안시 서북구","청양군","태안군","홍성군"],"충청북도":["괴산군","단양군","보은군","영동군","옥천군","음성군","제천시","증평군","진천군","청주시 상당구","청주시 서원구","청주시 청원구","청주시 흥덕구","충주시"],"대전광역시":["대덕구","동구","서구","유성구","중구"],"경상북도":["경산시","경주시","고령군","구미시","김천시","문경시","봉화군","상주시","성주군","안동시","영덕군","영양군","영주시","영천시","예천군","울릉군","울진군","의성군","청도군","청송군","칠곡군","포항시 남구","포항시 북구"],"대구광역시":["군위군","남구","달서구","달성군","동구","북구","서구","수성구","중구"],"전라남도":["강진군","고흥군","곡성군","광양시","구례군","나주시","담양군","목포시","무안군","보성군","순천시","신안군","여수시","영광군","영암군","완도군","장성군","장흥군","진도군","함평군","해남군","화순군"],"강원특별자치도":["강릉시","고성군","동해시","삼척시","속초시","양구군","양양군","영월군","원주시","인제군","정선군","철원군","춘천시","태백시","평창군","홍천군","화천군","횡성군"],"전북특별자치도":["고창군","군산시","김제시","남원시","무주군","부안군","순창군","완주군","익산시","임실군","장수군","전주시 덕진구","전주시 완산구","정읍시","진안군"],"울산광역시":["남구","동구","북구","울주군","중구"],"세종특별자치시":["세종특별자치시"],"광주광역시":["광산구","남구","동구","북구","서구"]},"lcls":["레저스포츠","문화관광","쇼핑","숙박","역사관광","음식","자연관광","체험관광","추천코스"],"mclsByLcls":{"문화관광":["공연시설","교육시설","기타문화관광지","도시.지역문화관광","도시공원","랜드마크관광","레저스포츠시설","복합관광시설","전시시설","테마공원"],"체험관광":["공예체험","기타체험","농.산.어촌 체험","산사체험","산업관광","웰니스관광","전통체험"],"쇼핑":["기타쇼핑시설","쇼핑몰","시장","전문매장/상가"],"자연관광":["기타자연관광","자연경관(산)","자연경관(하천‧해양)","자연공원","자연생태"],"역사관광":["안보관광지","역사유물","역사유적지","종교성지"],"숙박":["캠핑","콘도미니엄","펜션/민박","호스텔","호텔"],"레저스포츠":["복합레저스포츠","수상레저스포츠","육상레저스포츠","항공레저스포츠"],"음식":["카페/ 찻집","한식"],"추천코스":["캠핑코스"]},"nati":["전체","현지인","외지인"]},"kpis":{"nPoi":8588,"totalVisitors":33465709501.0,"totalEmission":28172754.0,"perPoiAvgKg":80011.7,"perCapitaKg":0.84,"top10Share":7.1,"lowCarbonCount":7345,"nSido":17,"nSgg":252},"national_monthly":[{"ym":"202301","visitors":732233988.0,"emission":616639.5},{"ym":"202302","visitors":712947280.0,"emission":602044.8},{"ym":"202303","visitors":839894314.0,"emission":701255.4},{"ym":"202304","visitors":826718610.0,"emission":691613.7},{"ym":"202305","visitors":878425569.0,"emission":734203.1},{"ym":"202306","visitors":820372066.0,"emission":685750.0},{"ym":"202307","visitors":798903410.0,"emission":669366.5},{"ym":"202308","visitors":822143368.0,"emission":689686.7},{"ym":"202309","visitors":813080240.0,"emission":676952.5},{"ym":"202310","visitors":895250332.0,"emission":749107.6},{"ym":"202311","visitors":747358409.0,"emission":625291.5},{"ym":"202312","visitors":728728976.0,"emission":617608.9},{"ym":"202401","visitors":702063548.0,"emission":593330.0},{"ym":"202402","visitors":687260024.0,"emission":579936.1},{"ym":"202403","visitors":800900054.0,"emission":671041.5},{"ym":"202404","visitors":816377415.0,"emission":680543.3},{"ym":"202405","visitors":879082519.0,"emission":734212.4},{"ym":"202406","visitors":811726615.0,"emission":678502.7},{"ym":"202407","visitors":788346394.0,"emission":659542.2},{"ym":"202408","visitors":852339674.0,"emission":722274.3},{"ym":"202409","visitors":838282767.0,"emission":705221.1},{"ym":"202410","visitors":915006116.0,"emission":772941.0},{"ym":"202411","visitors":824435412.0,"emission":695681.6},{"ym":"202412","visitors":765036573.0,"emission":651216.6},{"ym":"202501","visitors":745087374.0,"emission":634607.1},{"ym":"202502","visitors":679041206.0,"emission":577073.4},{"ym":"202503","visitors":820422008.0,"emission":690994.0},{"ym":"202504","visitors":825538046.0,"emission":694750.7},{"ym":"202505","visitors":947099968.0,"emission":799892.3},{"ym":"202506","visitors":861626972.0,"emission":724618.6},{"ym":"202507","visitors":860180594.0,"emission":725863.1},{"ym":"202508","visitors":897684816.0,"emission":760056.5},{"ym":"202509","visitors":844220580.0,"emission":707795.5},{"ym":"202510","visitors":927978412.0,"emission":785336.3},{"ym":"202511","visitors":871096250.0,"emission":734374.7},{"ym":"202512","visitors":794620992.0,"emission":675364.0},{"ym":"202601","visitors":745036285.0,"emission":632701.2},{"ym":"202602","visitors":724691198.0,"emission":615726.5},{"ym":"202603","visitors":841475282.0,"emission":707332.4},{"ym":"202604","visitors":834596850.0,"emission":702559.7},{"ym":"202605","visitors":948398994.0,"emission":799744.5}],"lclsRollup":[{"lcls":"문화관광","visitors":15245474790.0,"emission":11061640.5,"nPoi":2557,"share":39.3},{"lcls":"자연관광","visitors":8569824260.0,"emission":5218805.2,"nPoi":2366,"share":18.5},{"lcls":"역사관광","visitors":4645154227.0,"emission":4374564.3,"nPoi":2594,"share":15.5},{"lcls":"체험관광","visitors":1780539576.0,"emission":3817513.5,"nPoi":616,"share":13.6},{"lcls":"쇼핑","visitors":3007355505.0,"emission":3020708.9,"nPoi":343,"share":10.7},{"lcls":"숙박","visitors":79153116.0,"emission":435003.8,"nPoi":49,"share":1.5},{"lcls":"레저스포츠","visitors":88270532.0,"emission":168637.6,"nPoi":44,"share":0.6},{"lcls":"음식","visitors":45598483.0,"emission":62862.7,"nPoi":17,"share":0.2},{"lcls":"추천코스","visitors":4339013.0,"emission":13017.0,"nPoi":2,"share":0.0}],"mclsRollup":[{"mcls":"역사유적지","lcls":"역사관광","visitors":3190531113.0,"emission":3190531.3,"nPoi":1442,"share":11.3},{"mcls":"시장","lcls":"쇼핑","visitors":2955578112.0,"emission":2955578.1,"nPoi":333,"share":10.5},{"mcls":"도시공원","lcls":"문화관광","visitors":6752104418.0,"emission":2700841.6,"nPoi":792,"share":9.6},{"mcls":"전시시설","lcls":"문화관광","visitors":2967995471.0,"emission":2671195.9,"nPoi":960,"share":9.5},{"mcls":"기타체험","lcls":"체험관광","visitors":1291699510.0,"emission":2583399.1,"nPoi":285,"share":9.2},{"mcls":"자연경관(하천‧해양)","lcls":"자연관광","visitors":3527533394.0,"emission":2469273.4,"nPoi":1028,"share":8.8},{"mcls":"도시.지역문화관광","lcls":"문화관광","visitors":2539760640.0,"emission":2031808.5,"nPoi":213,"share":7.2},{"mcls":"자연경관(산)","lcls":"자연관광","visitors":2389145171.0,"emission":1433486.9,"nPoi":591,"share":5.1},{"mcls":"테마공원","lcls":"문화관광","visitors":1022022848.0,"emission":1328629.7,"nPoi":236,"share":4.7},{"mcls":"자연공원","lcls":"자연관광","visitors":2379709756.0,"emission":1189854.9,"nPoi":593,"share":4.2},{"mcls":"복합관광시설","lcls":"문화관광","visitors":843580104.0,"emission":1181012.1,"nPoi":77,"share":4.2},{"mcls":"종교성지","lcls":"역사관광","visitors":1298503402.0,"emission":1038802.7,"nPoi":1037,"share":3.7},{"mcls":"웰니스관광","lcls":"체험관광","visitors":294812346.0,"emission":766512.1,"nPoi":87,"share":2.7},{"mcls":"랜드마크관광","lcls":"문화관광","visitors":685227291.0,"emission":753750.0,"nPoi":186,"share":2.7},{"mcls":"호텔","lcls":"숙박","visitors":40621385.0,"emission":243728.3,"nPoi":13,"share":0.9},{"mcls":"산업관광","lcls":"체험관광","visitors":81120630.0,"emission":243361.9,"nPoi":73,"share":0.9},{"mcls":"농.산.어촌 체험","lcls":"체험관광","visitors":88918312.0,"emission":177836.6,"nPoi":149,"share":0.6},{"mcls":"콘도미니엄","lcls":"숙박","visitors":30312166.0,"emission":166716.9,"nPoi":9,"share":0.6},{"mcls":"육상레저스포츠","lcls":"레저스포츠","visitors":80908818.0,"emission":145635.9,"nPoi":36,"share":0.5},{"mcls":"공연시설","lcls":"문화관광","visitors":127045135.0,"emission":127045.1,"nPoi":14,"share":0.5},{"mcls":"기타문화관광지","lcls":"문화관광","visitors":142046824.0,"emission":113637.5,"nPoi":32,"share":0.4},{"mcls":"레저스포츠시설","lcls":"문화관광","visitors":94338699.0,"emission":103772.6,"nPoi":7,"share":0.4},{"mcls":"역사유물","lcls":"역사관광","visitors":108894650.0,"emission":98005.2,"nPoi":78,"share":0.3},{"mcls":"자연생태","lcls":"자연관광","visitors":189358295.0,"emission":75743.4,"nPoi":131,"share":0.3},{"mcls":"전문매장/상가","lcls":"쇼핑","visitors":44005255.0,"emission":52806.3,"nPoi":8,"share":0.2},{"mcls":"기타자연관광","lcls":"자연관광","visitors":84077644.0,"emission":50446.6,"nPoi":23,"share":0.2},{"mcls":"교육시설","lcls":"문화관광","visitors":71353359.0,"emission":49947.4,"nPoi":40,"share":0.2},{"mcls":"안보관광지","lcls":"역사관광","visitors":47225062.0,"emission":47225.1,"nPoi":37,"share":0.2},{"mcls":"한식","lcls":"음식","visitors":27148524.0,"emission":40722.8,"nPoi":3,"share":0.1},{"mcls":"전통체험","lcls":"체험관광","visitors":16434446.0,"emission":32868.9,"nPoi":17,"share":0.1},{"mcls":"카페/ 찻집","lcls":"음식","visitors":18449960.0,"emission":22140.0,"nPoi":14,"share":0.1},{"mcls":"캠핑","lcls":"숙박","visitors":6107780.0,"emission":15880.2,"nPoi":21,"share":0.1},{"mcls":"공예체험","lcls":"체험관광","visitors":7344918.0,"emission":13220.8,"nPoi":4,"share":0.0},{"mcls":"캠핑코스","lcls":"추천코스","visitors":4339013.0,"emission":13017.0,"nPoi":2,"share":0.0},{"mcls":"쇼핑몰","lcls":"쇼핑","visitors":7587332.0,"emission":12139.7,"nPoi":1,"share":0.0},{"mcls":"수상레저스포츠","lcls":"레저스포츠","visitors":4460306.0,"emission":11596.8,"nPoi":4,"share":0.0},{"mcls":"항공레저스포츠","lcls":"레저스포츠","visitors":1793494.0,"emission":8967.5,"nPoi":3,"share":0.0},{"mcls":"펜션/민박","lcls":"숙박","visitors":1287128.0,"emission":5792.1,"nPoi":5,"share":0.0},{"mcls":"호스텔","lcls":"숙박","visitors":824656.0,"emission":2886.3,"nPoi":1,"share":0.0},{"mcls":"복합레저스포츠","lcls":"레저스포츠","visitors":1107914.0,"emission":2437.4,"nPoi":1,"share":0.0},{"mcls":"산사체험","lcls":"체험관광","visitors":209412.0,"emission":314.1,"nPoi":1,"share":0.0},{"mcls":"기타쇼핑시설","lcls":"쇼핑","visitors":184807.0,"emission":184.8,"nPoi":1,"share":0.0}],"sidoRollup":[{"sido":"서울특별시","visitors":7714942095.0,"emission":6864000.9,"nPoi":675,"lon":126.978,"lat":37.5665},{"sido":"경기도","visitors":6708129214.0,"emission":5154957.2,"nPoi":1246,"lon":127.2,"lat":37.4138},{"sido":"경상남도","visitors":2585238372.0,"emission":2143156.2,"nPoi":901,"lon":128.2132,"lat":35.4606},{"sido":"강원특별자치도","visitors":2082839689.0,"emission":1938647.7,"nPoi":860,"lon":128.2,"lat":37.8228},{"sido":"부산광역시","visitors":2473320472.0,"emission":1922628.8,"nPoi":267,"lon":129.0756,"lat":35.1796},{"sido":"전라남도","visitors":1762241120.0,"emission":1520029.8,"nPoi":964,"lon":126.991,"lat":34.8679},{"sido":"인천광역시","visitors":1771424179.0,"emission":1415307.9,"nPoi":289,"lon":126.7052,"lat":37.4563},{"sido":"경상북도","visitors":1414784777.0,"emission":1215669.4,"nPoi":624,"lon":128.8889,"lat":36.4919},{"sido":"충청남도","visitors":1205268782.0,"emission":1060249.7,"nPoi":660,"lon":126.8,"lat":36.5184},{"sido":"대구광역시","visitors":1330150720.0,"emission":1038036.9,"nPoi":238,"lon":128.6014,"lat":35.8714},{"sido":"제주특별자치도","visitors":1087249138.0,"emission":1025666.2,"nPoi":448,"lon":126.5312,"lat":33.4996},{"sido":"전북특별자치도","visitors":1093108723.0,"emission":925613.4,"nPoi":642,"lon":127.1088,"lat":35.7175},{"sido":"대전광역시","visitors":706050754.0,"emission":626195.2,"nPoi":115,"lon":127.3845,"lat":36.3504},{"sido":"충청북도","visitors":619834988.0,"emission":524118.7,"nPoi":436,"lon":127.7,"lat":36.8},{"sido":"울산광역시","visitors":504600484.0,"emission":468150.7,"nPoi":132,"lon":129.3114,"lat":35.5384},{"sido":"광주광역시","visitors":311239842.0,"emission":238732.1,"nPoi":55,"lon":126.8526,"lat":35.1595},{"sido":"세종특별자치시","visitors":95286149.0,"emission":91592.6,"nPoi":36,"lon":127.289,"lat":36.4801}],"sggRollup":[{"sido":"서울특별시","sgg":"종로구","visitors":1223816688.0,"emission":1124293.1,"nPoi":113},{"sido":"서울특별시","sgg":"서초구","visitors":643843008.0,"emission":708659.7,"nPoi":35},{"sido":"서울특별시","sgg":"송파구","visitors":777249459.0,"emission":707496.5,"nPoi":33},{"sido":"인천광역시","sgg":"중구","visitors":779665845.0,"emission":673150.4,"nPoi":68},{"sido":"서울특별시","sgg":"중구","visitors":596765334.0,"emission":626177.4,"nPoi":55},{"sido":"서울특별시","sgg":"강남구","visitors":530417948.0,"emission":564218.9,"nPoi":46},{"sido":"제주특별자치도","sgg":"서귀포시","visitors":495555148.0,"emission":526718.4,"nPoi":204},{"sido":"서울특별시","sgg":"마포구","visitors":496488237.0,"emission":514703.7,"nPoi":32},{"sido":"경기도","sgg":"수원시 팔달구","visitors":527213442.0,"emission":504251.5,"nPoi":35},{"sido":"제주특별자치도","sgg":"제주시","visitors":591693991.0,"emission":498947.7,"nPoi":244},{"sido":"강원특별자치도","sgg":"속초시","visitors":411174432.0,"emission":454872.2,"nPoi":50},{"sido":"경상북도","sgg":"경주시","visitors":462656754.0,"emission":432327.7,"nPoi":69},{"sido":"강원특별자치도","sgg":"강릉시","visitors":453722304.0,"emission":342432.7,"nPoi":97},{"sido":"경상남도","sgg":"거제시","visitors":395682766.0,"emission":338684.1,"nPoi":116},{"sido":"전라남도","sgg":"목포시","visitors":297811910.0,"emission":320031.2,"nPoi":41},{"sido":"경기도","sgg":"화성시","visitors":419836148.0,"emission":316529.7,"nPoi":78},{"sido":"부산광역시","sgg":"해운대구","visitors":377157246.0,"emission":306799.1,"nPoi":19},{"sido":"전라남도","sgg":"여수시","visitors":349185816.0,"emission":302666.3,"nPoi":97},{"sido":"부산광역시","sgg":"중구","visitors":305643758.0,"emission":282685.3,"nPoi":19},{"sido":"대구광역시","sgg":"중구","visitors":354091633.0,"emission":279815.4,"nPoi":29},{"sido":"서울특별시","sgg":"광진구","visitors":257994944.0,"emission":265672.2,"nPoi":18},{"sido":"서울특별시","sgg":"영등포구","visitors":466613840.0,"emission":261858.2,"nPoi":22},{"sido":"경상남도","sgg":"통영시","visitors":322813050.0,"emission":261792.7,"nPoi":94},{"sido":"경상남도","sgg":"창원시 의창구","visitors":301033296.0,"emission":257170.8,"nPoi":45},{"sido":"인천광역시","sgg":"강화군","visitors":264266681.0,"emission":243034.1,"nPoi":87},{"sido":"서울특별시","sgg":"용산구","visitors":277700661.0,"emission":236034.6,"nPoi":35},{"sido":"대전광역시","sgg":"유성구","visitors":218885390.0,"emission":230074.6,"nPoi":31},{"sido":"경상남도","sgg":"김해시","visitors":258300644.0,"emission":220152.2,"nPoi":40},{"sido":"경기도","sgg":"시흥시","visitors":247311519.0,"emission":216375.8,"nPoi":38},{"sido":"부산광역시","sgg":"부산진구","visitors":309565672.0,"emission":214450.5,"nPoi":18},{"sido":"서울특별시","sgg":"서대문구","visitors":256380310.0,"emission":211172.2,"nPoi":17},{"sido":"경기도","sgg":"고양시 일산서구","visitors":174091138.0,"emission":205273.0,"nPoi":8},{"sido":"강원특별자치도","sgg":"춘천시","visitors":210162540.0,"emission":200564.3,"nPoi":60},{"sido":"경기도","sgg":"성남시 분당구","visitors":330874152.0,"emission":199132.5,"nPoi":25},{"sido":"전북특별자치도","sgg":"전주시 완산구","visitors":218717688.0,"emission":195875.2,"nPoi":35},{"sido":"경기도","sgg":"평택시","visitors":210091266.0,"emission":189913.5,"nPoi":38},{"sido":"서울특별시","sgg":"관악구","visitors":232184474.0,"emission":186629.2,"nPoi":27},{"sido":"부산광역시","sgg":"동래구","visitors":117245118.0,"emission":182803.2,"nPoi":16},{"sido":"경기도","sgg":"광주시","visitors":272842748.0,"emission":177341.1,"nPoi":47},{"sido":"경기도","sgg":"고양시 일산동구","visitors":241316145.0,"emission":174281.8,"nPoi":15},{"sido":"경상남도","sgg":"진주시","visitors":189457208.0,"emission":169614.6,"nPoi":50},{"sido":"인천광역시","sgg":"연수구","visitors":270313886.0,"emission":167780.5,"nPoi":21},{"sido":"대구광역시","sgg":"달서구","visitors":215296088.0,"emission":165779.8,"nPoi":26},{"sido":"대구광역시","sgg":"동구","visitors":205121084.0,"emission":165281.8,"nPoi":41},{"sido":"서울특별시","sgg":"성동구","visitors":191761280.0,"emission":162910.3,"nPoi":15},{"sido":"경기도","sgg":"김포시","visitors":197459227.0,"emission":162391.7,"nPoi":41},{"sido":"서울특별시","sgg":"양천구","visitors":251186660.0,"emission":162038.5,"nPoi":28},{"sido":"대전광역시","sgg":"중구","visitors":165230793.0,"emission":160926.2,"nPoi":22},{"sido":"경기도","sgg":"남양주시","visitors":251321679.0,"emission":159399.0,"nPoi":54},{"sido":"부산광역시","sgg":"금정구","visitors":216503868.0,"emission":153372.5,"nPoi":23},{"sido":"충청남도","sgg":"보령시","visitors":157160248.0,"emission":152625.2,"nPoi":71},{"sido":"경기도","sgg":"하남시","visitors":239153131.0,"emission":146627.3,"nPoi":16},{"sido":"서울특별시","sgg":"동대문구","visitors":171724878.0,"emission":146380.7,"nPoi":21},{"sido":"충청남도","sgg":"태안군","visitors":189747152.0,"emission":144613.5,"nPoi":97},{"sido":"울산광역시","sgg":"울주군","visitors":150300528.0,"emission":142726.3,"nPoi":54},{"sido":"서울특별시","sgg":"중랑구","visitors":183881358.0,"emission":138604.4,"nPoi":13},{"sido":"부산광역시","sgg":"기장군","visitors":165427612.0,"emission":136840.1,"nPoi":39},{"sido":"경기도","sgg":"안산시 단원구","visitors":166124147.0,"emission":136699.1,"nPoi":31},{"sido":"강원특별자치도","sgg":"양양군","visitors":147671188.0,"emission":134146.5,"nPoi":58},{"sido":"강원특별자치도","sgg":"삼척시","visitors":125975360.0,"emission":133947.4,"nPoi":72},{"sido":"서울특별시","sgg":"노원구","visitors":183841644.0,"emission":133079.3,"nPoi":21},{"sido":"대구광역시","sgg":"북구","visitors":192600012.0,"emission":132746.2,"nPoi":23},{"sido":"경상남도","sgg":"창원시 진해구","visitors":134577338.0,"emission":131914.8,"nPoi":34},{"sido":"경기도","sgg":"고양시 덕양구","visitors":150618590.0,"emission":131326.7,"nPoi":28},{"sido":"경기도","sgg":"양평군","visitors":170032146.0,"emission":130835.1,"nPoi":69},{"sido":"경기도","sgg":"파주시","visitors":210126360.0,"emission":130598.8,"nPoi":74},{"sido":"전북특별자치도","sgg":"군산시","visitors":156850774.0,"emission":127135.2,"nPoi":53},{"sido":"전라남도","sgg":"순천시","visitors":140011120.0,"emission":125804.1,"nPoi":54},{"sido":"경상북도","sgg":"포항시 북구","visitors":151811188.0,"emission":124822.3,"nPoi":27},{"sido":"서울특별시","sgg":"구로구","visitors":172885741.0,"emission":121370.5,"nPoi":22},{"sido":"서울특별시","sgg":"강서구","visitors":147587254.0,"emission":121192.8,"nPoi":21},{"sido":"경기도","sgg":"용인시 기흥구","visitors":190937047.0,"emission":121021.7,"nPoi":19},{"sido":"경기도","sgg":"이천시","visitors":120674858.0,"emission":120119.3,"nPoi":35},{"sido":"경기도","sgg":"용인시 처인구","visitors":108921732.0,"emission":115383.6,"nPoi":46},{"sido":"경기도","sgg":"수원시 장안구","visitors":154076920.0,"emission":114589.3,"nPoi":12},{"sido":"강원특별자치도","sgg":"동해시","visitors":129499251.0,"emission":114415.7,"nPoi":30},{"sido":"서울특별시","sgg":"강동구","visitors":182758278.0,"emission":114013.1,"nPoi":17},{"sido":"경기도","sgg":"여주시","visitors":123780122.0,"emission":111194.7,"nPoi":40},{"sido":"경상남도","sgg":"창원시 성산구","visitors":164720353.0,"emission":110842.2,"nPoi":16},{"sido":"경기도","sgg":"안성시","visitors":98570308.0,"emission":110361.6,"nPoi":50},{"sido":"대전광역시","sgg":"서구","visitors":180331795.0,"emission":110129.9,"nPoi":20},{"sido":"대전광역시","sgg":"동구","visitors":111882288.0,"emission":100061.9,"nPoi":27},{"sido":"울산광역시","sgg":"남구","visitors":99882783.0,"emission":99374.4,"nPoi":17},{"sido":"전북특별자치도","sgg":"남원시","visitors":98688370.0,"emission":99340.8,"nPoi":58},{"sido":"강원특별자치도","sgg":"원주시","visitors":123469178.0,"emission":98768.4,"nPoi":56},{"sido":"경기도","sgg":"양주시","visitors":156442850.0,"emission":98675.4,"nPoi":42},{"sido":"대구광역시","sgg":"수성구","visitors":121960384.0,"emission":97364.5,"nPoi":21},{"sido":"경상북도","sgg":"구미시","visitors":138853984.0,"emission":96173.3,"nPoi":38},{"sido":"강원특별자치도","sgg":"평창군","visitors":87749420.0,"emission":95261.7,"nPoi":55},{"sido":"부산광역시","sgg":"사하구","visitors":159961022.0,"emission":95056.3,"nPoi":15},{"sido":"경기도","sgg":"안양시 만안구","visitors":127844899.0,"emission":94302.1,"nPoi":16},{"sido":"경기도","sgg":"과천시","visitors":108397464.0,"emission":94054.5,"nPoi":20},{"sido":"충청남도","sgg":"아산시","visitors":86882128.0,"emission":92429.9,"nPoi":40},{"sido":"충청남도","sgg":"공주시","visitors":117221699.0,"emission":91787.1,"nPoi":58},{"sido":"세종특별자치시","sgg":"세종특별자치시","visitors":95286149.0,"emission":91592.6,"nPoi":36},{"sido":"충청남도","sgg":"서산시","visitors":99752100.0,"emission":89896.7,"nPoi":51},{"sido":"인천광역시","sgg":"서구","visitors":97913578.0,"emission":89072.0,"nPoi":13},{"sido":"충청남도","sgg":"부여군","visitors":93322736.0,"emission":86655.5,"nPoi":51},{"sido":"울산광역시","sgg":"중구","visitors":106766135.0,"emission":86482.4,"nPoi":25},{"sido":"경기도","sgg":"가평군","visitors":104006098.0,"emission":85721.0,"nPoi":68},{"sido":"부산광역시","sgg":"서구","visitors":118061391.0,"emission":84378.5,"nPoi":17},{"sido":"부산광역시","sgg":"동구","visitors":86413316.0,"emission":83670.4,"nPoi":20},{"sido":"경상남도","sgg":"사천시","visitors":109863936.0,"emission":81812.4,"nPoi":36},{"sido":"서울특별시","sgg":"동작구","visitors":113702334.0,"emission":81655.5,"nPoi":12},{"sido":"충청남도","sgg":"천안시 동남구","visitors":100343618.0,"emission":80987.2,"nPoi":36},{"sido":"광주광역시","sgg":"동구","visitors":96466062.0,"emission":80773.7,"nPoi":15},{"sido":"경기도","sgg":"부천시 원미구","visitors":154958248.0,"emission":80080.2,"nPoi":15},{"sido":"대구광역시","sgg":"남구","visitors":85652094.0,"emission":79942.8,"nPoi":19},{"sido":"경상남도","sgg":"밀양시","visitors":92222137.0,"emission":79839.3,"nPoi":29},{"sido":"부산광역시","sgg":"수영구","visitors":122457419.0,"emission":78913.3,"nPoi":8},{"sido":"충청북도","sgg":"제천시","visitors":79691437.0,"emission":78901.8,"nPoi":53},{"sido":"경기도","sgg":"구리시","visitors":102158896.0,"emission":76868.6,"nPoi":12},{"sido":"전북특별자치도","sgg":"익산시","visitors":79654246.0,"emission":75964.4,"nPoi":60},{"sido":"경기도","sgg":"의왕시","visitors":95030568.0,"emission":75487.3,"nPoi":17},{"sido":"서울특별시","sgg":"성북구","visitors":80779080.0,"emission":75258.8,"nPoi":21},{"sido":"경기도","sgg":"수원시 영통구","visitors":139714564.0,"emission":74493.1,"nPoi":14},{"sido":"경상남도","sgg":"양산시","visitors":83257808.0,"emission":74300.3,"nPoi":26},{"sido":"전라남도","sgg":"신안군","visitors":100015580.0,"emission":73210.5,"nPoi":74},{"sido":"전북특별자치도","sgg":"부안군","visitors":93241085.0,"emission":72748.3,"nPoi":41},{"sido":"대구광역시","sgg":"달성군","visitors":93048151.0,"emission":72645.8,"nPoi":48},{"sido":"울산광역시","sgg":"동구","visitors":78066590.0,"emission":72319.7,"nPoi":17},{"sido":"전라남도","sgg":"고흥군","visitors":114172982.0,"emission":71409.4,"nPoi":72},{"sido":"충청북도","sgg":"청주시 상당구","visitors":92192975.0,"emission":70540.9,"nPoi":34},{"sido":"전라남도","sgg":"완도군","visitors":90325560.0,"emission":70353.2,"nPoi":59},{"sido":"경상남도","sgg":"창원시 마산합포구","visitors":96877998.0,"emission":69913.8,"nPoi":17},{"sido":"경기도","sgg":"성남시 수정구","visitors":83962400.0,"emission":69006.0,"nPoi":13},{"sido":"강원특별자치도","sgg":"고성군","visitors":86076756.0,"emission":68424.3,"nPoi":55},{"sido":"전북특별자치도","sgg":"고창군","visitors":68888358.0,"emission":68188.9,"nPoi":53},{"sido":"부산광역시","sgg":"남구","visitors":97365541.0,"emission":67696.6,"nPoi":18},{"sido":"울산광역시","sgg":"북구","visitors":69584448.0,"emission":67247.9,"nPoi":19},{"sido":"경기도","sgg":"오산시","visitors":107780274.0,"emission":66910.9,"nPoi":18},{"sido":"인천광역시","sgg":"남동구","visitors":101772962.0,"emission":65782.2,"nPoi":11},{"sido":"서울특별시","sgg":"강북구","visitors":89248971.0,"emission":65761.0,"nPoi":15},{"sido":"전라남도","sgg":"진도군","visitors":77764057.0,"emission":65644.6,"nPoi":52},{"sido":"경기도","sgg":"안양시 동안구","visitors":106195747.0,"emission":65289.5,"nPoi":9},{"sido":"광주광역시","sgg":"북구","visitors":76522156.0,"emission":64768.8,"nPoi":17},{"sido":"충청북도","sgg":"충주시","visitors":74217437.0,"emission":64690.2,"nPoi":50},{"sido":"전라남도","sgg":"담양군","visitors":77655014.0,"emission":64320.6,"nPoi":38},{"sido":"경기도","sgg":"의정부시","visitors":89481234.0,"emission":64036.5,"nPoi":14},{"sido":"강원특별자치도","sgg":"정선군","visitors":47129383.0,"emission":63878.6,"nPoi":49},{"sido":"경기도","sgg":"군포시","visitors":110709347.0,"emission":63721.1,"nPoi":14},{"sido":"부산광역시","sgg":"영도구","visitors":81490178.0,"emission":63001.2,"nPoi":18},{"sido":"인천광역시","sgg":"미추홀구","visitors":94377367.0,"emission":62289.8,"nPoi":9},{"sido":"전북특별자치도","sgg":"전주시 덕진구","visitors":99360506.0,"emission":61584.8,"nPoi":15},{"sido":"경상북도","sgg":"문경시","visitors":68247711.0,"emission":59960.6,"nPoi":25},{"sido":"경기도","sgg":"포천시","visitors":62549070.0,"emission":59903.5,"nPoi":51},{"sido":"경상북도","sgg":"안동시","visitors":55613229.0,"emission":59665.5,"nPoi":42},{"sido":"충청북도","sgg":"단양군","visitors":68140163.0,"emission":59555.2,"nPoi":38},{"sido":"충청남도","sgg":"논산시","visitors":66639514.0,"emission":58351.2,"nPoi":49},{"sido":"부산광역시","sgg":"강서구","visitors":112202230.0,"emission":58189.4,"nPoi":19},{"sido":"경기도","sgg":"부천시 오정구","visitors":54797844.0,"emission":56684.5,"nPoi":13},{"sido":"경기도","sgg":"안산시 상록구","visitors":96575283.0,"emission":56215.3,"nPoi":13},{"sido":"충청북도","sgg":"청주시 흥덕구","visitors":65963796.0,"emission":54436.5,"nPoi":17},{"sido":"경기도","sgg":"광명시","visitors":76120474.0,"emission":53992.1,"nPoi":12},{"sido":"광주광역시","sgg":"서구","visitors":76456580.0,"emission":53982.9,"nPoi":8},{"sido":"충청남도","sgg":"당진시","visitors":61885992.0,"emission":52796.9,"nPoi":39},{"sido":"전북특별자치도","sgg":"정읍시","visitors":66100864.0,"emission":52256.9,"nPoi":53},{"sido":"서울특별시","sgg":"은평구","visitors":73837600.0,"emission":52020.4,"nPoi":13},{"sido":"경기도","sgg":"부천시 소사구","visitors":51989063.0,"emission":51569.5,"nPoi":7},{"sido":"강원특별자치도","sgg":"영월군","visitors":47231618.0,"emission":51135.6,"nPoi":71},{"sido":"경기도","sgg":"수원시 권선구","visitors":80414170.0,"emission":50702.1,"nPoi":14},{"sido":"충청북도","sgg":"괴산군","visitors":58530496.0,"emission":50281.2,"nPoi":72},{"sido":"경상북도","sgg":"상주시","visitors":68675120.0,"emission":49676.2,"nPoi":55},{"sido":"강원특별자치도","sgg":"태백시","visitors":51934964.0,"emission":49231.3,"nPoi":27},{"sido":"전라남도","sgg":"화순군","visitors":62672852.0,"emission":48754.5,"nPoi":46},{"sido":"경상남도","sgg":"합천군","visitors":61322884.0,"emission":48520.6,"nPoi":55},{"sido":"충청남도","sgg":"예산군","visitors":46817320.0,"emission":48040.1,"nPoi":30},{"sido":"경상남도","sgg":"창녕군","visitors":57860495.0,"emission":47653.4,"nPoi":37},{"sido":"인천광역시","sgg":"옹진군","visitors":64347976.0,"emission":46987.6,"nPoi":59},{"sido":"전라남도","sgg":"나주시","visitors":68023655.0,"emission":46815.8,"nPoi":45},{"sido":"충청남도","sgg":"홍성군","visitors":49630690.0,"emission":46370.2,"nPoi":30},{"sido":"전라남도","sgg":"영광군","visitors":56714231.0,"emission":46055.5,"nPoi":36},{"sido":"경상북도","sgg":"영덕군","visitors":67283412.0,"emission":45929.8,"nPoi":38},{"sido":"전북특별자치도","sgg":"완주군","visitors":61515828.0,"emission":45322.3,"nPoi":56},{"sido":"전라남도","sgg":"해남군","visitors":50572144.0,"emission":44698.2,"nPoi":50},{"sido":"충청남도","sgg":"금산군","visitors":50068508.0,"emission":44343.8,"nPoi":35},{"sido":"전라남도","sgg":"보성군","visitors":33794649.0,"emission":44239.8,"nPoi":34},{"sido":"경기도","sgg":"용인시 수지구","visitors":76800818.0,"emission":44118.3,"nPoi":12},{"sido":"부산광역시","sgg":"연제구","visitors":85238374.0,"emission":42570.3,"nPoi":6},{"sido":"부산광역시","sgg":"북구","visitors":66911310.0,"emission":42460.4,"nPoi":5},{"sido":"경기도","sgg":"성남시 중원구","visitors":59925866.0,"emission":42354.9,"nPoi":12},{"sido":"경상남도","sgg":"하동군","visitors":49145488.0,"emission":42230.0,"nPoi":57},{"sido":"서울특별시","sgg":"금천구","visitors":53474950.0,"emission":42080.9,"nPoi":11},{"sido":"서울특별시","sgg":"도봉구","visitors":58817168.0,"emission":40719.2,"nPoi":12},{"sido":"경상북도","sgg":"영주시","visitors":44040308.0,"emission":40305.8,"nPoi":37},{"sido":"경상남도","sgg":"고성군","visitors":47788370.0,"emission":39833.0,"nPoi":29},{"sido":"전북특별자치도","sgg":"무주군","visitors":39623766.0,"emission":39781.0,"nPoi":36},{"sido":"경상북도","sgg":"울진군","visitors":36821309.0,"emission":39562.0,"nPoi":29},{"sido":"경상남도","sgg":"남해군","visitors":49866474.0,"emission":38714.4,"nPoi":53},{"sido":"경상북도","sgg":"포항시 남구","visitors":50148920.0,"emission":37801.6,"nPoi":24},{"sido":"경기도","sgg":"동두천시","visitors":36644027.0,"emission":37158.4,"nPoi":9},{"sido":"인천광역시","sgg":"계양구","visitors":54948016.0,"emission":34306.1,"nPoi":11},{"sido":"충청남도","sgg":"서천군","visitors":38134166.0,"emission":33509.9,"nPoi":38},{"sido":"전북특별자치도","sgg":"김제시","visitors":44582678.0,"emission":33454.9,"nPoi":57},{"sido":"전라남도","sgg":"강진군","visitors":38999104.0,"emission":32713.7,"nPoi":43},{"sido":"전라남도","sgg":"무안군","visitors":46248951.0,"emission":31919.5,"nPoi":26},{"sido":"경상남도","sgg":"거창군","visitors":34023185.0,"emission":31801.0,"nPoi":21},{"sido":"강원특별자치도","sgg":"홍천군","visitors":32958846.0,"emission":31367.8,"nPoi":24},{"sido":"부산광역시","sgg":"사상구","visitors":51676418.0,"emission":29741.6,"nPoi":7},{"sido":"강원특별자치도","sgg":"철원군","visitors":39976094.0,"emission":29506.9,"nPoi":39},{"sido":"경상남도","sgg":"함양군","visitors":49119616.0,"emission":29286.8,"nPoi":38},{"sido":"대구광역시","sgg":"서구","visitors":44320916.0,"emission":28715.2,"nPoi":11},{"sido":"광주광역시","sgg":"광산구","visitors":46224927.0,"emission":28617.0,"nPoi":7},{"sido":"경상남도","sgg":"산청군","visitors":37044438.0,"emission":28419.7,"nPoi":51},{"sido":"전라남도","sgg":"영암군","visitors":29589724.0,"emission":28116.2,"nPoi":24},{"sido":"경상북도","sgg":"경산시","visitors":36137692.0,"emission":27524.2,"nPoi":19},{"sido":"경상북도","sgg":"청송군","visitors":26899470.0,"emission":26805.8,"nPoi":19},{"sido":"전라남도","sgg":"광양시","visitors":28251867.0,"emission":26417.0,"nPoi":30},{"sido":"경상북도","sgg":"고령군","visitors":29035279.0,"emission":25559.2,"nPoi":21},{"sido":"대전광역시","sgg":"대덕구","visitors":29720488.0,"emission":25002.6,"nPoi":15},{"sido":"충청북도","sgg":"보은군","visitors":33058284.0,"emission":24956.3,"nPoi":31},{"sido":"충청북도","sgg":"옥천군","visitors":29647415.0,"emission":24279.3,"nPoi":29},{"sido":"충청북도","sgg":"음성군","visitors":26695424.0,"emission":23322.5,"nPoi":30},{"sido":"경상북도","sgg":"청도군","visitors":21494848.0,"emission":23141.1,"nPoi":23},{"sido":"충청북도","sgg":"청주시 청원구","visitors":30543474.0,"emission":22562.3,"nPoi":7},{"sido":"강원특별자치도","sgg":"화천군","visitors":28074862.0,"emission":22168.5,"nPoi":38},{"sido":"경상북도","sgg":"울릉군","visitors":25046360.0,"emission":21492.0,"nPoi":24},{"sido":"전북특별자치도","sgg":"임실군","visitors":25624386.0,"emission":21453.6,"nPoi":32},{"sido":"강원특별자치도","sgg":"인제군","visitors":30211174.0,"emission":20943.9,"nPoi":31},{"sido":"경상북도","sgg":"김천시","visitors":30914548.0,"emission":20574.2,"nPoi":19},{"sido":"전라남도","sgg":"장흥군","visitors":29240050.0,"emission":20564.1,"nPoi":38},{"sido":"경상남도","sgg":"함안군","visitors":26101929.0,"emission":20406.6,"nPoi":34},{"sido":"경기도","sgg":"연천군","visitors":20257184.0,"emission":19965.8,"nPoi":32},{"sido":"전라남도","sgg":"곡성군","visitors":26642007.0,"emission":19761.4,"nPoi":33},{"sido":"인천광역시","sgg":"부평구","visitors":23275280.0,"emission":19413.5,"nPoi":5},{"sido":"경상북도","sgg":"칠곡군","visitors":22957274.0,"emission":19217.7,"nPoi":21},{"sido":"경상북도","sgg":"영천시","visitors":22326006.0,"emission":18893.3,"nPoi":29},{"sido":"강원특별자치도","sgg":"횡성군","visitors":14319330.0,"emission":17030.3,"nPoi":26},{"sido":"전라남도","sgg":"구례군","visitors":20393768.0,"emission":16588.1,"nPoi":34},{"sido":"경상북도","sgg":"성주군","visitors":20433728.0,"emission":16236.2,"nPoi":10},{"sido":"대구광역시","sgg":"군위군","visitors":18060357.0,"emission":15745.2,"nPoi":20},{"sido":"충청남도","sgg":"천안시 서북구","visitors":18971302.0,"emission":15166.2,"nPoi":6},{"sido":"충청북도","sgg":"영동군","visitors":17285051.0,"emission":15044.8,"nPoi":27},{"sido":"충청북도","sgg":"진천군","visitors":18520901.0,"emission":14444.7,"nPoi":24},{"sido":"경상북도","sgg":"의성군","visitors":14185374.0,"emission":13980.1,"nPoi":21},{"sido":"전북특별자치도","sgg":"진안군","visitors":17375757.0,"emission":13899.2,"nPoi":37},{"sido":"인천광역시","sgg":"동구","visitors":20542588.0,"emission":13491.7,"nPoi":5},{"sido":"충청남도","sgg":"계룡시","visitors":18448378.0,"emission":13108.2,"nPoi":9},{"sido":"경상남도","sgg":"의령군","visitors":15767566.0,"emission":13079.0,"nPoi":20},{"sido":"충청북도","sgg":"증평군","visitors":13941403.0,"emission":11100.9,"nPoi":16},{"sido":"전라남도","sgg":"장성군","visitors":9821010.0,"emission":10751.6,"nPoi":19},{"sido":"광주광역시","sgg":"남구","visitors":15570118.0,"emission":10589.7,"nPoi":8},{"sido":"강원특별자치도","sgg":"양구군","visitors":15502991.0,"emission":10551.6,"nPoi":22},{"sido":"충청북도","sgg":"청주시 서원구","visitors":11406731.0,"emission":10002.0,"nPoi":8},{"sido":"경상북도","sgg":"예천군","visitors":11943144.0,"emission":9648.2,"nPoi":15},{"sido":"전북특별자치도","sgg":"장수군","visitors":11250816.0,"emission":9583.2,"nPoi":28},{"sido":"충청남도","sgg":"청양군","visitors":10243233.0,"emission":9568.1,"nPoi":20},{"sido":"전라남도","sgg":"함평군","visitors":14335069.0,"emission":9194.4,"nPoi":19},{"sido":"전북특별자치도","sgg":"순창군","visitors":11633601.0,"emission":9024.8,"nPoi":28},{"sido":"경상남도","sgg":"창원시 마산회원구","visitors":8391394.0,"emission":7174.5,"nPoi":3},{"sido":"경상북도","sgg":"봉화군","visitors":6410677.0,"emission":3810.9,"nPoi":10},{"sido":"경상북도","sgg":"영양군","visitors":2848440.0,"emission":2562.0,"nPoi":9}],"top10":[{"id":"264570","nm":"강남","sido":"서울특별시","sgg":"서초구","visitors":209914810.0,"emission":419829.62},{"id":"2711042","nm":"인천국제공항","sido":"인천광역시","sgg":"중구","visitors":224159645.5,"emission":246575.61},{"id":"781031","nm":"홍대","sido":"서울특별시","sgg":"마포구","visitors":119103512.5,"emission":238207.02},{"id":"1957612","nm":"목포 관광특구","sido":"전라남도","sgg":"목포시","visitors":116095738.5,"emission":162534.03},{"id":"992130","nm":"키자니아 서울","sido":"서울특별시","sgg":"송파구","visitors":79961924.0,"emission":159923.85},{"id":"264311","nm":"명동","sido":"서울특별시","sgg":"중구","visitors":79299731.0,"emission":158599.46},{"id":"126823","nm":"압구정 로데오거리","sido":"서울특별시","sgg":"강남구","visitors":79141895.0,"emission":158283.79},{"id":"2456640","nm":"고양 관광특구","sido":"경기도","sgg":"고양시 일산서구","visitors":107829519.0,"emission":150961.33},{"id":"2480899","nm":"수원화성 관광특구","sido":"경기도","sgg":"수원시 팔달구","visitors":107497309.5,"emission":150496.23},{"id":"264353","nm":"인사동","sido":"서울특별시","sgg":"종로구","visitors":73986797.5,"emission":147973.6}]}